jupyros/__init__.py
jupyros/_version.py
jupyros/ros1/__init__.py
jupyros/ros1/ipy.py
jupyros/ros1/pubsub.py
jupyros/ros1/ros3d.py
jupyros/ros1/ros_widgets.py
jupyros/ros1/server_extension.py
jupyros/ros1/turtle_sim.py
jupyros/ros2/__init__.py
jupyros/ros2/ipy.py
jupyros/ros2/key_input.py
jupyros/ros2/publisher.py
jupyros/ros2/ros_widgets.py
jupyros/ros2/subscriber.py
jupyros/ros2/turtle_sim.py
jupyros-0.7.0.data/data/etc/jupyter/jupyter_notebook_config.d/jupyros_nbserver_extension.json
jupyros-0.7.0.data/data/etc/jupyter/nbconfig/notebook.d/jupyter-ros.json
jupyros-0.7.0.data/data/share/jupyter/labextensions/@robostack/jupyter-ros/build_log.json
jupyros-0.7.0.data/data/share/jupyter/labextensions/@robostack/jupyter-ros/package.json
jupyros-0.7.0.data/data/share/jupyter/labextensions/@robostack/jupyter-ros/static/lib_labplugin_js.bffa1ef142940408a4e8.js
jupyros-0.7.0.data/data/share/jupyter/labextensions/@robostack/jupyter-ros/static/remoteEntry.594a540deb642597a0ce.js
jupyros-0.7.0.data/data/share/jupyter/labextensions/@robostack/jupyter-ros/static/style.js
jupyros-0.7.0.data/data/share/jupyter/labextensions/@robostack/jupyter-ros/static/vendors-node_modules_jupyter-widgets_base_lib_index_js.73e2f412a1ac85317168.js
jupyros-0.7.0.data/data/share/jupyter/labextensions/@robostack/jupyter-ros/static/vendors-node_modules_lodash_lodash_js.91a1c274e5e60c72cd52.js
jupyros-0.7.0.data/data/share/jupyter/labextensions/@robostack/jupyter-ros/static/vendors-node_modules_ros3d_build_ros3d_esm_js.760f4bf663c96ed65f42.js
jupyros-0.7.0.data/data/share/jupyter/labextensions/@robostack/jupyter-ros/static/vendors-node_modules_roslib_src_RosLib_js.1898b30ea16d9d9dcec0.js
jupyros-0.7.0.data/data/share/jupyter/labextensions/@robostack/jupyter-ros/static/vendors-node_modules_three_build_three_module_js.23750f16ca76d6f06c6e.js
jupyros-0.7.0.data/data/share/jupyter/nbextensions/@robostack/jupyter-ros/extension.js
jupyros-0.7.0.dist-info/METADATA
jupyros-0.7.0.dist-info/WHEEL
jupyros-0.7.0.dist-info/licenses/LICENSE
jupyros-0.7.0.dist-info/RECORD
