Metadata-Version: 2.1
Name: jupyros
Version: 0.7.0
Summary: Jupyter widgets for the ROS ecosystem.
Project-URL: Homepage, https://github.com/wolfv/jupyter-ros.git
Project-URL: Repository, https://github.com/wolfv/jupyter-ros.git
Author-email: Wolf Vollprecht <w.vollprecht@gmail.com>
License: Copyright (c) 2016, Wolf Vollprecht
License-File: LICENSE
Classifier: Framework :: Jupyter
Classifier: Framework :: Jupyter :: JupyterLab
Classifier: Framework :: Jupyter :: JupyterLab :: 4
Classifier: Framework :: Jupyter :: JupyterLab :: Extensions
Classifier: Framework :: Jupyter :: JupyterLab :: Extensions :: Prebuilt
Classifier: Intended Audience :: Developers
Classifier: Intended Audience :: Science/Research
Classifier: Intended Audience :: System Administrators
Classifier: License :: OSI Approved :: BSD License
Classifier: Programming Language :: Python
Classifier: Programming Language :: Python :: 3.8
Classifier: Programming Language :: Python :: 3.9
Classifier: Programming Language :: Python :: 3.10
Classifier: Programming Language :: Python :: 3.11
Requires-Python: >=3.8
Requires-Dist: bqplot
Requires-Dist: ipycanvas
Requires-Dist: ipywidgets<8.0.0,>=7.7.2
Requires-Dist: numpy
Requires-Dist: rospkg
Provides-Extra: dev
Requires-Dist: click; extra == 'dev'
Requires-Dist: jupyter-releaser==0.22; extra == 'dev'
Requires-Dist: pre-commit; extra == 'dev'
